base_folder/__init__.py
base_folder/browser.py
base_folder/definition.py
base_folder/locators.py
hellosmalldemo/__init__.py
hellosmalldemo/hello.py
spreadsheetsmalldemo/__init__.py
spreadsheetsmalldemo/browser.py
spreadsheetsmalldemo/definition.py
spreadsheetsmalldemo/sites.py
spreadsheetsmalldemo/test.py
spreadsheetsmalldemo/example/__init__.py
spreadsheetsmalldemo/example/bot.py
spreadsheetsmalldemo/example/locators.py
spreadsheetsmalldemo/rpa/__init__.py
spreadsheetsmalldemo/rpa/ui/__init__.py
spreadsheetsmalldemo/rpa/ui/ui.py
vidstream/__init__.py
vidstream/audio.py
vidstream/streaming.py
vidstreamtestdemo/__init__.py
vidstreamtestdemo/audio.py
vidstreamtestdemo/streaming.py
spreadsheetsmalldemo-0.0.17.dist-info/LICENSE
spreadsheetsmalldemo-0.0.17.dist-info/METADATA
spreadsheetsmalldemo-0.0.17.dist-info/WHEEL
spreadsheetsmalldemo-0.0.17.dist-info/top_level.txt
spreadsheetsmalldemo-0.0.17.dist-info/RECORD
